Metadata-Version: 2.1
Name: parsa
Version: 1.1.5
Summary: A multiformat text parser
Home-page: http://github.com/rdimaio/parsa
Author: Riccardo Di Maio
Author-email: riccardodimaio11@gmail.com
License: MIT
Keywords: parsa
Platform: UNKNOWN
Classifier: Development Status :: 5 - Production/Stable
Classifier: Environment :: Console
Classifier: Intended Audience :: Developers
Classifier: Intended Audience :: Information Technology
Classifier: Intended Audience :: Science/Research
Classifier: Intended Audience :: System Administrators
Classifier: Intended Audience :: Other Audience
Classifier: Programming Language :: Python :: 2.7
Classifier: Programming Language :: Python :: 3
Classifier: License :: OSI Approved :: MIT License
Classifier: Operating System :: POSIX
Classifier: Topic :: Text Processing
Classifier: Topic :: Utilities
